Metadata-Version: 1.1
Name: hurm.fe
Version: 0.9
Summary: Human Resources Manager, ExtJS frontend
Home-page: https://bitbucket.org/lele/hurm.fe
Author: Lele Gaifax
Author-email: lele@metapensiero.it
License: GPLv3+
Keywords: web wsgi bfg pylons pyramid
Platform: UNKNOWN
Classifier: Development Status :: 3 - Alpha
Classifier: Programming Language :: Python
Classifier: Programming Language :: Python :: 3
Classifier: Programming Language :: Python :: 3.5
Classifier: Framework :: Pyramid
Classifier: Topic :: Internet :: WWW/HTTP
Classifier: Topic :: Internet :: WWW/HTTP :: WSGI :: Application
Classifier: Programming Language :: JavaScript
Classifier: Operating System :: OS Independent
Classifier: Intended Audience :: End Users/Desktop
Classifier: License :: OSI Approved :: GNU General Public License v3 or later (GPLv3+)
